subspace/__init__.py
subspace/cache.py
subspace/constants.py
subspace/exceptions.py
subspace/executor.py
subspace/runner.py
subspace/stats.py
subspace/task_queue_manager.py
subspace/version.py
subspace/plugins/__init__.py
subspace/plugins/callback/__init__.py
subspace/plugins/callback/play_logger.py
subspace/plugins/strategy/__init__.py
subspace/plugins/strategy/subspace.py
subspace-0.5.1.dist-info/DESCRIPTION.rst
subspace-0.5.1.dist-info/METADATA
subspace-0.5.1.dist-info/RECORD
subspace-0.5.1.dist-info/WHEEL
subspace-0.5.1.dist-info/metadata.json
subspace-0.5.1.dist-info/top_level.txt
