Metadata-Version: 2.0
Name: subspace
Version: 0.5.1
Summary: A pragmatic interface to programmatically use Ansible.
Home-page: https://github.com/iPlantCollaborativeOpenSource/subspace
Author: iPlant Collaborative
Author-email: atmodevs@gmail.com
License: Apache License, Version 2.0
Platform: UNKNOWN
Classifier: Development Status :: 4 - Beta
Classifier: Intended Audience :: Developers
Classifier: Intended Audience :: Information Technology
Classifier: License :: OSI Approved :: Apache Software License
Classifier: Operating System :: OS Independent
Classifier: Programming Language :: Python
Classifier: Topic :: Software Development :: Libraries
Classifier: Topic :: System
Classifier: Topic :: System :: Clustering
Classifier: Topic :: System :: Distributed Computing
Classifier: Topic :: System :: Systems Administration
Requires-Dist: ansible (>=2.3.0.0)
Requires-Dist: redis (>=2.10.3)
